textcompari/README.MD
textcompari/__init__.py
textcompari/requirements.txt
textcompari/textpari.pyx
textcompari/thirdparty.json
textcompari-0.10.dist-info/LICENSE.rst
textcompari-0.10.dist-info/METADATA
textcompari-0.10.dist-info/WHEEL
textcompari-0.10.dist-info/top_level.txt
textcompari-0.10.dist-info/RECORD
