Metadata-Version: 2.1
Name: textcompari
Version: 0.10
Summary: A function to get the difference between two files and return a pandas DataFrame
Home-page: https://github.com/hansalemaos/textcompari
Author: Johannes Fischer
Author-email: aulasparticularesdealemaosp@gmail.com
License: MIT
Keywords: diff,files,pandas,DataFrame
Classifier: Development Status :: 4 - Beta
Classifier: Programming Language :: Python :: 3 :: Only
Classifier: Programming Language :: Python :: 3.10
Classifier: Topic :: Software Development :: Libraries :: Python Modules
Classifier: Topic :: Utilities
License-File: LICENSE.rst
Requires-Dist: cycompi
Requires-Dist: numexpr
Requires-Dist: numpy
Requires-Dist: numpycythonpermutations
Requires-Dist: pandas
Requires-Dist: rapidfuzz
